wnhelloworldpackage/__init__.py
wnhelloworldpackage-0.1.dist-info/LICENSE
wnhelloworldpackage-0.1.dist-info/METADATA
wnhelloworldpackage-0.1.dist-info/WHEEL
wnhelloworldpackage-0.1.dist-info/top_level.txt
wnhelloworldpackage-0.1.dist-info/RECORD
