Metadata-Version: 2.1
Name: wnhelloworldpackage
Version: 0.1
Summary: hello world!
Home-page: https://github.com/wnetel/helloworld
Author: Witold Netel
Author-email: wnetel901@gmail.com
License: UNKNOWN
Platform: UNKNOWN
Classifier: Programming Language :: Python :: 3
Classifier: License :: OSI Approved :: MIT License
Classifier: Operating System :: OS Independent
